uedoc_theme/__init__.py
uedoc_theme/globaltoc.html
uedoc_theme/header.html
uedoc_theme/layout.html
uedoc_theme/localtoc.html
uedoc_theme/search.html
uedoc_theme/searchbox.html
uedoc_theme/theme.conf
uedoc_theme/static/css/theme.css
uedoc_theme/static/fonts/BrutalType-Regular.625db3d6423e7c39f2c46e57da023ac9.svg
uedoc_theme/static/fonts/BrutalType-Regular.7bc10a83799597dfeed8f31b2caafc89.woff2
uedoc_theme/static/fonts/BrutalType-Regular.9901514add9ae673fcc81872b03a80f9.ttf
uedoc_theme/static/fonts/BrutalType-Regular.b9848a2312d7272470bc6b1728e58dd7.eot
uedoc_theme/static/fonts/BrutalType-Regular.fb64664a41f9789dfab9377a68505cc3.woff
uedoc_theme/static/fonts/open-sans-v17-latin-regular.1d0d8b66fa1da76d69b95b6d0ed5cca9.svg
uedoc_theme/static/fonts/open-sans-v17-latin-regular.347639ec49f4b2884a9657afded83ace.woff
uedoc_theme/static/fonts/open-sans-v17-latin-regular.b9e56724ef49012eeb57bf453a940881.eot
uedoc_theme/static/fonts/open-sans-v17-latin-regular.cf6a34547195e0972978eab2aa4d2fb2.ttf
uedoc_theme/static/fonts/open-sans-v17-latin-regular.f57a62e9efddf6ace18b15572f81905b.woff2
uedoc_theme/static/js/theme.js
sphinx_uedoc_theme-0.1.2.dist-info/LICENSE
sphinx_uedoc_theme-0.1.2.dist-info/METADATA
sphinx_uedoc_theme-0.1.2.dist-info/WHEEL
sphinx_uedoc_theme-0.1.2.dist-info/top_level.txt
sphinx_uedoc_theme-0.1.2.dist-info/RECORD
