Metadata-Version: 2.1
Name: sphinx-uedoc-theme
Version: 0.1.2
Summary: Unreal engine documentation theme for Python Sphinx
Home-page: https://github.com/Raider-Arts/sphinx-uedoc-theme
Author: Luca Faggion
Author-email: luc-af@live.it
License: UNKNOWN
Platform: UNKNOWN
Classifier: Programming Language :: Python :: 3
Classifier: License :: OSI Approved :: MIT License
Classifier: Operating System :: OS Independent
Requires-Python: >=3.6
Requires-Dist: sphinx
